<?xml version = '1.0' encoding = 'UTF-8'?>
<Diagram class="oracle.dbtools.crest.swingui.datatypes.DPVDataTypes" id="E6C9CF2B-9EFF-76A1-B5AF-10E76AF85687">
<createdBy>franc</createdBy>
<modifiedBy>franc</modifiedBy>
<createdTime>2024-09-17 01:50:56 UTC</createdTime>
<autoRoute>false</autoRoute>
<boxInbox>true</boxInbox>
<showLegend>false</showLegend>
<showLabels>true</showLabels>
<showRelAttributes>false</showRelAttributes>
<gridEnabled>false</gridEnabled>
<showGrid>false</showGrid>
<diagramColor>-1</diagramColor>
<display>false</display>
<notation>1</notation>
<objectViews>
<OView class="oracle.dbtools.crest.swingui.datatypes.TVStructuredType" oid="47E390DE-0671-C4B1-8428-0F45CBEE18F8" otype="StructuredType" vid="62124D36-9812-CB5C-1619-D7815007ED49">
<hideElementsInCurrentOnly>false</hideElementsInCurrentOnly>
<bounds x="20" y="20" width="100" height="100"/>
</OView>
<OView class="oracle.dbtools.crest.swingui.datatypes.TVStructuredType" oid="F72C39E0-D1CA-8821-2AD7-A1E95A37D3D1" otype="StructuredType" vid="98521465-E1AA-D423-E925-392E95C53533">
<hideElementsInCurrentOnly>false</hideElementsInCurrentOnly>
<bounds x="20" y="20" width="100" height="100"/>
</OView>
</objectViews>
</Diagram>